lisptorch_core.cpython-311-x86_64-linux-gnu.so
lisptorch-0.1.9.dist-info/METADATA
lisptorch-0.1.9.dist-info/WHEEL
lisptorch-0.1.9.dist-info/top_level.txt
lisptorch-0.1.9.dist-info/RECORD
