Metadata-Version: 2.4
Name: lisptorch
Version: 0.1.9
Requires-Dist: pybind11
Dynamic: description
Dynamic: description-content-type
Dynamic: requires-dist
